{
  "kind": "kitty",
  "id": "kitty-kovidgoyal-dark-pastel",
  "name": "Dark Pastel",
  "description": "Dark Pastel kitty theme from kovidgoyal/kitty-themes.",
  "mode": "dark",
  "source": {
    "id": "kovidgoyal",
    "name": "kovidgoyal/kitty-themes",
    "repository": "https://github.com/kovidgoyal/kitty-themes",
    "path": "themes/Dark_Pastel.conf",
    "url": "https://github.com/kovidgoyal/kitty-themes/blob/f54e894cce7c2232c8af9a82f85dca874e496da1/themes/Dark_Pastel.conf",
    "commit": "f54e894cce7c2232c8af9a82f85dca874e496da1",
    "license": "GPL-3.0"
  },
  "palette": {
    "background": "#000000",
    "foreground": "#ffffff",
    "cursor": "#bbbbbb",
    "selectionBackground": "#b5d5ff",
    "selectionForeground": "#000000",
    "color0": "#000000",
    "color1": "#ff5555",
    "color2": "#55ff55",
    "color3": "#ffff55",
    "color4": "#5555ff",
    "color5": "#ff55ff",
    "color6": "#55ffff",
    "color7": "#bbbbbb",
    "color8": "#545454",
    "color9": "#ff5555",
    "color10": "#55ff55",
    "color11": "#ffff55",
    "color12": "#5555ff",
    "color13": "#ff55ff",
    "color14": "#55ffff",
    "color15": "#ffffff"
  }
}
